setup.py
shinkenplugins/__init__.py
shinkenplugins.plugins.drupal_logging.egg-info/PKG-INFO
shinkenplugins.plugins.drupal_logging.egg-info/SOURCES.txt
shinkenplugins.plugins.drupal_logging.egg-info/dependency_links.txt
shinkenplugins.plugins.drupal_logging.egg-info/entry_points.txt
shinkenplugins.plugins.drupal_logging.egg-info/namespace_packages.txt
shinkenplugins.plugins.drupal_logging.egg-info/requires.txt
shinkenplugins.plugins.drupal_logging.egg-info/top_level.txt
shinkenplugins/plugins/__init__.py
shinkenplugins/plugins/drupal_logging/__init__.py
shinkenplugins/plugins/drupal_logging/drupal_logging.py